tests/__init__.py
tests/tests_convertor.py
tests/tests_generator.py
waterbear/__init__.py
waterbear/convertor.py
waterbear/generator.py
waterbear/utils/__init__.py
waterbear/utils/util.py
dbl_waterbear-0.1.1.dist-info/LICENSE
dbl_waterbear-0.1.1.dist-info/METADATA
dbl_waterbear-0.1.1.dist-info/NOTICE
dbl_waterbear-0.1.1.dist-info/WHEEL
dbl_waterbear-0.1.1.dist-info/top_level.txt
dbl_waterbear-0.1.1.dist-info/RECORD
